mapepire_python/__init__.py
mapepire_python/base_job.py
mapepire_python/data_types.py
mapepire_python/py.typed
mapepire_python/query_manager.py
mapepire_python/ssl.py
mapepire_python/version.py
mapepire_python/websocket.py
mapepire_python/asyncio/__init__.py
mapepire_python/asyncio/connection.py
mapepire_python/asyncio/cursor.py
mapepire_python/asyncio/utils.py
mapepire_python/client/__init__.py
mapepire_python/client/query.py
mapepire_python/client/sql_job.py
mapepire_python/client/websocket_client.py
mapepire_python/core/__init__.py
mapepire_python/core/connection.py
mapepire_python/core/cursor.py
mapepire_python/core/exceptions.py
mapepire_python/core/utils.py
mapepire_python/pool/__init__.py
mapepire_python/pool/async_websocket_client.py
mapepire_python/pool/pool_client.py
mapepire_python/pool/pool_job.py
mapepire_python/pool/pool_query.py
mapepire_python-0.2.0.dist-info/LICENSE
mapepire_python-0.2.0.dist-info/METADATA
mapepire_python-0.2.0.dist-info/WHEEL
mapepire_python-0.2.0.dist-info/top_level.txt
mapepire_python-0.2.0.dist-info/RECORD
